README.md
setup.py
RoboBurp2.egg-info/PKG-INFO
RoboBurp2.egg-info/SOURCES.txt
RoboBurp2.egg-info/dependency_links.txt
RoboBurp2.egg-info/requires.txt
RoboBurp2.egg-info/top_level.txt
roboburp2/RoboBurp2.py