Metadata-Version: 2.1
Name: RoboBurp2
Version: 1.1
Summary: Robot Framework Library for the BurpSuite Pro Vulnerability Scanner
Home-page: https://www.github.com/we45/RoboBurp2
Author: we45
Author-email: info@we45.com
License: MIT
Platform: UNKNOWN
